uvicorn_worker/__init__.py
uvicorn_worker/py.typed
uvicorn_worker-0.1.0.dist-info/METADATA
uvicorn_worker-0.1.0.dist-info/WHEEL
uvicorn_worker-0.1.0.dist-info/RECORD
