Metadata-Version: 2.1
Name: uvicorn-worker
Version: 0.1.0
Summary: Uvicorn worker for Gunicorn ⚙️
Author-email: Marcelo Trylesinski <marcelotryle@gmail.com>
License: MIT
